{
	"info": {
		"_postman_id": "3a585638-d5c7-4ce2-813b-0b1cf156eb72",
		"name": "Blog Pessoal T41",
		"schema": "https://schema.getpostman.com/json/collection/v2.1.0/collection.json"
	},
	"item": [
		{
			"name": "Postagem",
			"item": [
				{
					"name": "Get By Id",
					"request": {
						"method": "GET",
						"header": [],
						"url": {
							"raw": "http://localhost:8080/postagens/1",
							"protocol": "http",
							"host": [
								"localhost"
							],
							"port": "8080",
							"path": [
								"postagens",
								"1"
							]
						}
					},
					"response": []
				},
				{
					"name": "Get By Titulo",
					"request": {
						"method": "GET",
						"header": [],
						"url": {
							"raw": "http://localhost:8080/postagens/titulo/segunda",
							"protocol": "http",
							"host": [
								"localhost"
							],
							"port": "8080",
							"path": [
								"postagens",
								"titulo",
								"segunda"
							]
						}
					},
					"response": []
				},
				{
					"name": "Post postagem",
					"request": {
						"method": "POST",
						"header": [],
						"body": {
							"mode": "raw",
							"raw": "{\r\n    \"titulo\": \"Meu Primeiro Titulo Post Insertion\",\r\n    \"texto\" : \"Meu Primeiro Texto Post da Postagem\"\r\n}",
							"options": {
								"raw": {
									"language": "json"
								}
							}
						},
						"url": {
							"raw": "http://localhost:8080/postagens",
							"protocol": "http",
							"host": [
								"localhost"
							],
							"port": "8080",
							"path": [
								"postagens"
							]
						}
					},
					"response": []
				},
				{
					"name": "Atualizar postagem",
					"request": {
						"method": "PUT",
						"header": [],
						"body": {
							"mode": "raw",
							"raw": "{\r\n    \"id\" : \"3\",\r\n    \"titulo\": \"Meu Primeiro Titulo Post Insertion - atualizado\",\r\n    \"texto\" : \"Meu Primeiro Texto Post da Postagem - atualizada\"\r\n}",
							"options": {
								"raw": {
									"language": "json"
								}
							}
						},
						"url": {
							"raw": "http://localhost:8080/postagens",
							"protocol": "http",
							"host": [
								"localhost"
							],
							"port": "8080",
							"path": [
								"postagens"
							]
						}
					},
					"response": []
				},
				{
					"name": "Deletar Postagem",
					"request": {
						"method": "DELETE",
						"header": [],
						"url": {
							"raw": "http://localhost:8080/postagens/4",
							"protocol": "http",
							"host": [
								"localhost"
							],
							"port": "8080",
							"path": [
								"postagens",
								"4"
							]
						}
					},
					"response": []
				}
			]
		}
	]
}